{
    "Name": "Όνομα",
    "Object": "Αντικείμενο",
    "Category": "Κατηγορία",
    "States": "Κατάσταση",
    "Attributes": "Χαρακτηριστικό",
    "Events": "Γεγονός",
    "Flags": "Ιδιότητα",
    "Collisions": "Σύγκρουση",
    "Search": "Αναζήτηση",
    "Snapshot": "Στιγμιότυπο",
    "Delta State": "Δ State",
    "Click to Stop Recording": "Πατήστε για Παύση",
    "Recording": "Εγγραφή",
    "Current Recording": "Τωρινή εγγραφή",
    "Playback Speed": "Ταχύτητα Επανάληψης",
    "Frame": "Καρέ",
    "Time": "Χρόνος",
    "Jump to recording": "Πήγαινε στην εγγραφή",
    "Continue with new recording": "Συνέχισε με νέα εγγραφή",
    "Scripts for object": "Scripts για το αντικείμενο",
    "Stage": "Σκηνή",
    "Keyboard": "Πληκτρολόγιο",
    "Rectangle": "Παρ/μο",
    "Circle": "Κύκλος",
    "Square": "Τετράγωνο",
    "Text": "Κείμενο",
    "Live Assets" : "Ενεργά Στοιχεία",
    "Animations": "Κινούμενα Σχέδια",
    "Objects": "Αντικείμενα",
    "Clipboard": "Πρόχειρο",
    "Snapshots": "Στιγμιότυπα",
    "Scenes": "Σκηνές",
    "Films": "Φιλμς",
    "Nothing to be shown": "Δεν υπάρχουν διαθέσιμα αντικείμενα",
    "Clear All": "Καθάρισμα",
    "Remove All": "Διαγραφή Όλων",
    "Animation Workshop": "Εργαστήριο Σχεδίων",
    "Delay": "Καθυστέρηση",
    "Dx": "Δx",
    "Dy": "Δy",
    "Repetitions": "Επαναλήψεις",
    "Animation": "Σχέδιο",
    "Reset Position": "Επαναφορά στο κέντρο",
    "Replay Animation": "Επανάληψη κίνησης",
    "Create Animation": "Δημιουργία σχεδίου",
    "Update Animation": "Ανανέωση Animation",
    "Remove Animation": "Διαγραφή σχεδίου",
    "Colors": "Χρώματα",
    "AddOns": "Πρόσθετα",
    "KeyBinds": "Κουμπιά",
    "Options": "Επιλογές",
    "No description provided": "Δεν υπάρχει διαθέσιμη περιγραφή",
    "Main color": "Κύριο χρώμα",
    "Main color (hover)": "Κύριο χρώμα (hover)",
    "Main color (text)": "Κύριο χρώμα (κείμενο)",
    "Secondary color": "Δευτερέυων χρώμα",
    "Secondary color (hover)": "Δευτερέυων χρώμα (hover)",
    "Secondary color (text)": "Δευτερέυων χρώμα (κείμενο)",
    "System Language": "Γλώσσα συστήματος",
    "Preview of this object isn't possible": "Δεν είναι δυνατή η παρουσίαση αυτού του αντικειμένου",
    "Dragging Objects": "Μετακίνηση αντικειμένων με το ποντίκι",
    "Clicking Through Objects": "Click στα πίσω αντικείμενα",
    "Move UI with Control": "Μετακίνηση UI πατώντας το control",
    "Only show objects in search": "Αναζήτηση μόνο αντικειμένων",
    "Show Prompt On Actions": "Εμφάνηση μηνύματος στις ενέργειες",
    "Show Action Feedback": "Εμφάνηση μηνύματος ανατροφοδότησης",
    "Copy Object": "Αντιγραφή αντικειμένου",
    "Paste Object": "Επικόλληση αντικειμένου",
    "Remove Object": "Διαγραφή αντικειμένου",
    "Take Object Snapshot": "Λήψη στιγμιότυπο αντικειμένου",
    "Take Scene Snapshot": "Λήψη στιγμιότυπο σκηνής",
    "If you accept": "Με την αποδοχή",
    "object": "το αντικείμενο",
    "will get removed": "θα διαγραφεί",
    "Accept": "Αποδοχή",
    "Decline": "Απόρριψη",
    "animation": "το σχεδιο",
    "Clear Clipboard": "Καθάρισμα πρόχειρου",
    "ALL": "όλό",
    "clipboard": "το πρόχειρο",
    "will get cleared": "θα καθαριστούν",
    "item": "το αντικείμενο",
    "Remove Item": "Διαγραφή αντικειμένου",
    "Create Object": "Εισαγωγή αντικειμένου",
    "a": "ένα",
    "copy": "αντίγραφο",
    "of": "του",
    "will be created": "θα δημιουργηθεί",
    "Reset Scene": "Επαναφορά σκηνής",
    "scene": "η σκηνή",
    "will get resetted": "θα επαναφερθεί",
    "Remove All Snapshot": "Διαγραφή όλων των στιμιοτύπων",
    "snapshot": "στιγμιότυπo",
    "every": "κάθε",
    "Remove Snapshot": "Διαγραφή στιγμιοτύπου",
    "the current": "το συγκεκριμένο",
    "Reset Object": "Επαναφορά αντικειμένου",
    "Continue From Recording": "Συνέχιση απο την εγγραφή",
    "recording": "εγγραφή",
    "you will lose": "θα χάσεις",
    "and": "και",
    "New Recording": "Νέα εγγραφή",
    "continue from stop point": "θα συνεχίσεις απο το σημείο που έχεις σταματήσει",
    "all the recordings": "όλες τις εγγραφές",
    "after timeline": "μετά απο την εγγραφή",
    "Go To Homepage": "Πήγαινε στην αρχική σελίδα",
    "you will be redirected": "θα φύγεις απο την σελίδα",
    "all the progress": "όλη την πρόοδο",
    "if you haven't saved": "αν δεν έχεις κάνει αποθήκευση"
}